test_python_200123/__init__.py
test_python_200123/cli.py
test_python_200123/slims.py
test_python_200123-0.1.0.dist-info/DESCRIPTION.rst
test_python_200123-0.1.0.dist-info/METADATA
test_python_200123-0.1.0.dist-info/RECORD
test_python_200123-0.1.0.dist-info/WHEEL
test_python_200123-0.1.0.dist-info/entry_points.txt
test_python_200123-0.1.0.dist-info/metadata.json
test_python_200123-0.1.0.dist-info/top_level.txt
